flask_lucide/__init__.py
flask_lucide/extension.py
flask_lucide/icons.py
flask_lucide-0.2.0.dist-info/LICENSE
flask_lucide-0.2.0.dist-info/METADATA
flask_lucide-0.2.0.dist-info/WHEEL
flask_lucide-0.2.0.dist-info/top_level.txt
flask_lucide-0.2.0.dist-info/RECORD
