Metadata-Version: 2.1
Name: flask-lucide
Version: 0.2.0
Summary: A simple Tag to implement Lucide Icons in Flask
Home-page: https://github.com/WAKayser/flask-lucide
Author: Wouter Kayser
Author-email: wouterkayser@gmail.com
License: UNKNOWN
Platform: UNKNOWN
Classifier: Development Status :: 3 - Alpha
Classifier: Framework :: Flask
Classifier: License :: OSI Approved :: Apache Software License
Classifier: Programming Language :: Python
Classifier: Programming Language :: Python :: 3
Classifier: Programming Language :: Python :: 3.6
Classifier: Programming Language :: Python :: 3.7
Classifier: Programming Language :: Python :: 3.8
Classifier: Programming Language :: Python :: 3.9
Classifier: Operating System :: OS Independent
Provides-Extra: dev
License-File: LICENSE
